pytest_llm_report/__about__.py
pytest_llm_report/__init__.py
pytest_llm_report/_git_info.py
pytest_llm_report/aggregation.py
pytest_llm_report/cache.py
pytest_llm_report/collector.py
pytest_llm_report/context_util.py
pytest_llm_report/coverage_map.py
pytest_llm_report/errors.py
pytest_llm_report/models.py
pytest_llm_report/options.py
pytest_llm_report/plugin.py
pytest_llm_report/prompts.py
pytest_llm_report/render.py
pytest_llm_report/report_writer.py
pytest_llm_report/llm/__init__.py
pytest_llm_report/llm/annotator.py
pytest_llm_report/llm/base.py
pytest_llm_report/llm/batching.py
pytest_llm_report/llm/gemini.py
pytest_llm_report/llm/litellm_provider.py
pytest_llm_report/llm/noop.py
pytest_llm_report/llm/ollama.py
pytest_llm_report/llm/schemas.py
pytest_llm_report/llm/token_refresh.py
pytest_llm_report/llm/utils.py
pytest_llm_report/templates/report.html.j2
pytest_llm_report/templates/report.js
pytest_llm_report/templates/style.css
pytest_llm_report/templates/summary.html.j2
pytest_llm_report/templates/test_row.html.j2
pytest_llm_report/templates/components/badges.html.j2
pytest_llm_report/templates/components/coverage_list.html.j2
pytest_llm_report/templates/components/filters.html.j2
pytest_llm_report/util/__init__.py
pytest_llm_report/util/fs.py
pytest_llm_report/util/hashing.py
pytest_llm_report/util/ranges.py
pytest_llm_report/util/time.py
pytest_llm_report-0.2.1.dist-info/METADATA
pytest_llm_report-0.2.1.dist-info/WHEEL
pytest_llm_report-0.2.1.dist-info/entry_points.txt
pytest_llm_report-0.2.1.dist-info/licenses/LICENSE
pytest_llm_report-0.2.1.dist-info/RECORD
