Metadata-Version: 2.4
Name: pytest-llm-report
Version: 0.2.1
Summary: Human-friendly pytest test reports with optional LLM annotations
Project-URL: Homepage, https://github.com/palakpsheth/pytest-llm-report
Project-URL: Documentation, https://palakpsheth.github.io/pytest-llm-report/
Project-URL: Repository, https://github.com/palakpsheth/pytest-llm-report
Project-URL: Issues, https://github.com/palakpsheth/pytest-llm-report/issues
Author: pytest-llm-report contributors
License-Expression: MIT
License-File: LICENSE
Keywords: coverage,llm,pytest,report,testing
Classifier: Development Status :: 3 - Alpha
Classifier: Framework :: Pytest
Classifier: Intended Audience :: Developers
Classifier: License :: OSI Approved :: MIT License
Classifier: Operating System :: OS Independent
Classifier: Programming Language :: Python :: 3
Classifier: Programming Language :: Python :: 3.11
Classifier: Programming Language :: Python :: 3.12
Classifier: Programming Language :: Python :: 3.13
Classifier: Topic :: Software Development :: Testing
Requires-Python: >=3.11
Requires-Dist: coverage>=7.0.0
Requires-Dist: jinja2>=3.0.0
Requires-Dist: pytest-cov>=4.0.0
Requires-Dist: pytest>=7.0.0
Provides-Extra: all
Requires-Dist: httpx>=0.24.0; extra == 'all'
Requires-Dist: litellm>=1.0.0; extra == 'all'
Requires-Dist: mypy>=1.0.0; extra == 'all'
Requires-Dist: playwright>=1.40.0; extra == 'all'
Requires-Dist: pytest-xdist>=3.0.0; extra == 'all'
Requires-Dist: ruff>=0.1.0; extra == 'all'
Requires-Dist: urllib3>=2.6.3; extra == 'all'
Provides-Extra: dev
Requires-Dist: httpx>=0.24.0; extra == 'dev'
Requires-Dist: litellm>=1.0.0; extra == 'dev'
Requires-Dist: mypy>=1.0.0; extra == 'dev'
Requires-Dist: playwright>=1.40.0; extra == 'dev'
Requires-Dist: pytest-xdist>=3.0.0; extra == 'dev'
Requires-Dist: ruff>=0.1.0; extra == 'dev'
Requires-Dist: urllib3>=2.6.3; extra == 'dev'
Provides-Extra: gemini
Requires-Dist: httpx>=0.24.0; extra == 'gemini'
Requires-Dist: urllib3>=2.6.3; extra == 'gemini'
Provides-Extra: litellm
Requires-Dist: litellm>=1.0.0; extra == 'litellm'
Provides-Extra: ollama
Requires-Dist: httpx>=0.24.0; extra == 'ollama'
Requires-Dist: urllib3>=2.6.3; extra == 'ollama'
Provides-Extra: pdf
Requires-Dist: playwright>=1.40.0; extra == 'pdf'
